README.md
setup.py
avilabs_ml_metrics.egg-info/PKG-INFO
avilabs_ml_metrics.egg-info/SOURCES.txt
avilabs_ml_metrics.egg-info/dependency_links.txt
avilabs_ml_metrics.egg-info/top_level.txt
examples/__init__.py
examples/example.py
mlmetrics/__init__.py
mlmetrics/metric.py
mlmetrics/sqlitemetrics/__init__.py
mlmetrics/sqlitemetrics/sqlite_metric.py