Metadata-Version: 2.1
Name: avilabs-ml-metrics
Version: 1.1.0
Summary: Metrics for Machine Learning
Home-page: https://gitlab.com/avilay/ml-metrics
Author: Avilay Parekh
Author-email: avilay@gmail.com
License: MIT
Platform: UNKNOWN
